README.md
setup.py
archs/__init__.py
archs/arcface_arch.py
archs/arch_util.py
archs/codeformer_arch.py
archs/rrdbnet_arch.py
archs/vgg_arch.py
archs/vqgan_arch.py
data/__init__.py
data/data_sampler.py
data/data_util.py
data/prefetch_dataloader.py
data/transforms.py
losses/__init__.py
losses/loss_util.py
losses/losses.py
metrics/__init__.py
metrics/metric_util.py
metrics/psnr_ssim.py
models/__init__.py
ops/__init__.py
ops/dcn/__init__.py
ops/dcn/deform_conv.py
ops/fused_act/__init__.py
ops/fused_act/fused_act.py
ops/upfirdn2d/__init__.py
ops/upfirdn2d/upfirdn2d.py
utils/__init__.py
utils/dist_util.py
utils/download_util.py
utils/file_client.py
utils/img_util.py
utils/lmdb_util.py
utils/logger.py
utils/matlab_functions.py
utils/misc.py
utils/options.py
utils/realesrgan_utils.py
utils/registry.py
vyro_custom_basicsr.egg-info/PKG-INFO
vyro_custom_basicsr.egg-info/SOURCES.txt
vyro_custom_basicsr.egg-info/dependency_links.txt
vyro_custom_basicsr.egg-info/not-zip-safe
vyro_custom_basicsr.egg-info/requires.txt
vyro_custom_basicsr.egg-info/top_level.txt