Metadata-Version: 2.1
Name: vyro-custom-basicsr
Version: 1.4.2
Summary: Open Source Image and Video Super-Resolution Toolbox
Home-page: https://github.com/xinntao/BasicSR
Author: Xintao Wang
Author-email: xintao.wang@outlook.com
License: Apache License 2.0
Keywords: computer vision,restoration,super resolution
Platform: UNKNOWN
Classifier: Development Status :: 4 - Beta
Classifier: License :: OSI Approved :: Apache Software License
Classifier: Operating System :: OS Independent
Classifier: Programming Language :: Python :: 3
Classifier: Programming Language :: Python :: 3.7
Classifier: Programming Language :: Python :: 3.8
